upload_validator/__init__.py
django_upload_validator-1.1.6.dist-info/LICENSE
django_upload_validator-1.1.6.dist-info/METADATA
django_upload_validator-1.1.6.dist-info/WHEEL
django_upload_validator-1.1.6.dist-info/top_level.txt
django_upload_validator-1.1.6.dist-info/RECORD
