Metadata-Version: 2.1
Name: django-upload-validator
Version: 1.1.6
Summary: A simple Django file type validator using python-magic
Home-page: https://github.com/naeem91/django-upload-validator
Author: Naeem Ilyas
Author-email: naeem-ilyas@live.com
License: MIT
Platform: UNKNOWN
License-File: LICENSE
